blade_templating/__init__.py
blade_templating/__main__.py
blade_templating/driver.py
blade_templating/worker.py
blade_templating/common/__init__.py
blade_templating/common/blob.py
blade_templating/common/generation.py
blade_templating/common/logging.py
blade_templating/common/rules.py
blu_blade_templating-1.0.dist-info/LICENSE
blu_blade_templating-1.0.dist-info/METADATA
blu_blade_templating-1.0.dist-info/WHEEL
blu_blade_templating-1.0.dist-info/entry_points.txt
blu_blade_templating-1.0.dist-info/top_level.txt
blu_blade_templating-1.0.dist-info/RECORD
