Metadata-Version: 2.1
Name: blu-blade-templating
Version: 1.0
Summary: Templating Engine for Generating Hardware from BLADE Output Blobs Based on Mako
Home-page: https://www.bluwireless.com
Author: Blu Wireless Ltd
License: GNU General Public License v3.0
Project-URL: Source, https://github.com/bluwireless/blade-templating
Project-URL: Tracker, https://github.com/bluwireless/blade-templating/issues
Platform: UNKNOWN
Requires-Dist: designformat
Requires-Dist: pyyaml
Requires-Dist: mako
Requires-Dist: tqdm
Provides-Extra: documentation
Requires-Dist: sphinx ; extra == 'documentation'
Requires-Dist: recommonmark ; extra == 'documentation'
Requires-Dist: sphinx-markdown-tables ; extra == 'documentation'
Requires-Dist: sphinx-rtd-theme ; extra == 'documentation'
